LICENSE
README.md
setup.cfg
setup.py
pymsteams/__init__.py
pymsteams_workflow.egg-info/PKG-INFO
pymsteams_workflow.egg-info/SOURCES.txt
pymsteams_workflow.egg-info/dependency_links.txt
pymsteams_workflow.egg-info/requires.txt
pymsteams_workflow.egg-info/top_level.txt
test/test_workflow.py