Metadata-Version: 2.1
Name: pymsteams-workflow
Version: 1.0.4
Summary: Format messages and post to Microsoft Teams through Microsoft Power Automate WorkFlow.
Home-page: https://github.com/mroussamamessabih-1337/pymsteams/
Author: Oussama Messabih
Author-email: oussamamessabih02@gmail.com
License: Apache
Keywords: Microsoft,Teams,Power,Automate,Workflow
Classifier: Development Status :: 5 - Production/Stable
Classifier: Intended Audience :: Developers
Classifier: Intended Audience :: Information Technology
Classifier: Intended Audience :: System Administrators
Classifier: License :: OSI Approved :: Apache Software License
Classifier: Operating System :: OS Independent
Classifier: Topic :: Software Development :: Libraries :: Python Modules
Classifier: Topic :: Internet
Classifier: Programming Language :: Python :: 3
Classifier: Topic :: Office/Business
Classifier: Topic :: Office/Business :: Groupware
Requires-Python: >=3.6
License-File: LICENSE
Requires-Dist: requests>=2.20.0
Provides-Extra: async
Requires-Dist: httpx>=0.18.2; extra == "async"
